llama_github/__init__.py
llama_github/github_rag.py
llama_github/logger.py
llama_github/utils.py
llama_github/version.py
llama_github/config/__init__.py
llama_github/config/config.json
llama_github/config/config.py
llama_github/data_retrieval/__init__.py
llama_github/data_retrieval/github_api.py
llama_github/data_retrieval/github_entities.py
llama_github/features/__init__.py
llama_github/features/feature_flags.py
llama_github/features/insider_features.py
llama_github/github_integration/__init__.py
llama_github/github_integration/github_auth_manager.py
llama_github/llm_integration/__init__.py
llama_github/llm_integration/initial_load.py
llama_github/llm_integration/llm_handler.py
llama_github/rag_processing/__init__.py
llama_github/rag_processing/rag_processor.py
llama_github-0.3.3.dist-info/licenses/LICENSE
llama_github-0.3.3.dist-info/METADATA
llama_github-0.3.3.dist-info/WHEEL
llama_github-0.3.3.dist-info/top_level.txt
llama_github-0.3.3.dist-info/RECORD
