Metadata-Version: 2.4
Name: llama-github
Version: 0.3.3
Summary: Llama-github is an open-source Python library that empowers LLM Chatbots, AI Agents, and Auto-dev Agents to conduct Retrieval from actively selected GitHub public projects. It Augments through LLMs and Generates context for any coding question, in order to streamline the development of sophisticated AI-driven applications.
Home-page: https://github.com/JetXu-LLM/llama-github
Author: Jet Xu
Author-email: Voldemort.xu@foxmail.com
Classifier: Programming Language :: Python :: 3
Classifier: License :: OSI Approved :: Apache Software License
Classifier: Operating System :: OS Independent
Requires-Python: >=3.6
License-File: LICENSE
Requires-Dist: aiohttp
Requires-Dist: asyncio
Requires-Dist: PyGithub
Requires-Dist: langchain
Requires-Dist: numpy
Requires-Dist: pydantic
Requires-Dist: requests
Requires-Dist: transformers
Requires-Dist: urllib3
Requires-Dist: pydantic_core
Requires-Dist: langchain_openai
Requires-Dist: langchain_mistralai
Requires-Dist: httpx_sse
Requires-Dist: tokenizers
Provides-Extra: dev
Requires-Dist: pytest; extra == "dev"
Requires-Dist: black; extra == "dev"
Requires-Dist: flake8; extra == "dev"
Dynamic: license-file
Dynamic: requires-dist
